{
 "custom_fields": [
  {
   "_assign": null,
   "_comments": null,
   "_liked_by": null,
   "_user_tags": null,
   "allow_in_quick_entry": 0,
   "allow_on_submit": 0,
   "bold": 0,
   "collapsible": 0,
   "collapsible_depends_on": null,
   "columns": 0,
   "creation": "2023-11-24 12:25:37.576958",
   "default": null,
   "depends_on": null,
   "description": null,
   "docstatus": 0,
   "dt": "Delivery Note",
   "fetch_from": "company.tax_id",
   "fetch_if_empty": 0,
   "fieldname": "company_trn",
   "fieldtype": "Read Only",
   "hidden": 0,
   "hide_border": 0,
   "hide_days": 0,
   "hide_seconds": 0,
   "idx": 0,
   "ignore_user_permissions": 0,
   "ignore_xss_filter": 0,
   "in_global_search": 0,
   "in_list_view": 0,
   "in_preview": 0,
   "in_standard_filter": 0,
   "insert_after": "company_address",
   "is_system_generated": 1,
   "is_virtual": 0,
   "label": "Company TRN",
   "length": 0,
   "mandatory_depends_on": null,
   "modified": "2023-11-24 12:25:37.576958",
   "modified_by": "Administrator",
   "module": null,
   "name": "Delivery Note-company_trn",
   "no_copy": 0,
   "non_negative": 0,
   "options": null,
   "owner": "Administrator",
   "permlevel": 0,
   "precision": "",
   "print_hide": 1,
   "print_hide_if_no_value": 0,
   "print_width": null,
   "read_only": 0,
   "read_only_depends_on": null,
   "report_hide": 0,
   "reqd": 0,
   "search_index": 0,
   "sort_options": 0,
   "translatable": 1,
   "unique": 0,
   "width": null
  },
  {
   "_assign": null,
   "_comments": null,
   "_liked_by": null,
   "_user_tags": null,
   "allow_in_quick_entry": 0,
   "allow_on_submit": 0,
   "bold": 0,
   "collapsible": 0,
   "collapsible_depends_on": null,
   "columns": 0,
   "creation": "2023-11-24 12:25:37.580543",
   "default": null,
   "depends_on": null,
   "description": null,
   "docstatus": 0,
   "dt": "Delivery Note",
   "fetch_from": "customer.customer_name_in_arabic",
   "fetch_if_empty": 0,
   "fieldname": "customer_name_in_arabic",
   "fieldtype": "Read Only",
   "hidden": 0,
   "hide_border": 0,
   "hide_days": 0,
   "hide_seconds": 0,
   "idx": 0,
   "ignore_user_permissions": 0,
   "ignore_xss_filter": 0,
   "in_global_search": 0,
   "in_list_view": 0,
   "in_preview": 0,
   "in_standard_filter": 0,
   "insert_after": "customer_name",
   "is_system_generated": 1,
   "is_virtual": 0,
   "label": "Customer Name in Arabic",
   "length": 0,
   "mandatory_depends_on": null,
   "modified": "2023-11-24 12:25:37.580543",
   "modified_by": "Administrator",
   "module": null,
   "name": "Delivery Note-customer_name_in_arabic",
   "no_copy": 0,
   "non_negative": 0,
   "options": null,
   "owner": "Administrator",
   "permlevel": 0,
   "precision": "",
   "print_hide": 1,
   "print_hide_if_no_value": 0,
   "print_width": null,
   "read_only": 0,
   "read_only_depends_on": null,
   "report_hide": 0,
   "reqd": 0,
   "search_index": 0,
   "sort_options": 0,
   "translatable": 1,
   "unique": 0,
   "width": null
  },
  {
   "_assign": null,
   "_comments": null,
   "_liked_by": null,
   "_user_tags": null,
   "allow_in_quick_entry": 0,
   "allow_on_submit": 0,
   "bold": 0,
   "collapsible": 0,
   "collapsible_depends_on": null,
   "columns": 0,
   "creation": "2023-11-24 12:25:37.584197",
   "default": null,
   "depends_on": null,
   "description": null,
   "docstatus": 0,
   "dt": "Delivery Note",
   "fetch_from": null,
   "fetch_if_empty": 0,
   "fieldname": "ksa_einv_qr",
   "fieldtype": "Attach Image",
   "hidden": 1,
   "hide_border": 0,
   "hide_days": 0,
   "hide_seconds": 0,
   "idx": 0,
   "ignore_user_permissions": 0,
   "ignore_xss_filter": 0,
   "in_global_search": 0,
   "in_list_view": 0,
   "in_preview": 0,
   "in_standard_filter": 0,
   "insert_after": null,
   "is_system_generated": 1,
   "is_virtual": 0,
   "label": "KSA E-Invoicing QR",
   "length": 0,
   "mandatory_depends_on": null,
   "modified": "2023-11-24 12:25:37.584197",
   "modified_by": "Administrator",
   "module": null,
   "name": "Delivery Note-ksa_einv_qr",
   "no_copy": 1,
   "non_negative": 0,
   "options": null,
   "owner": "Administrator",
   "permlevel": 0,
   "precision": "",
   "print_hide": 0,
   "print_hide_if_no_value": 0,
   "print_width": null,
   "read_only": 1,
   "read_only_depends_on": null,
   "report_hide": 0,
   "reqd": 0,
   "search_index": 0,
   "sort_options": 0,
   "translatable": 1,
   "unique": 0,
   "width": null
  },
  {
   "_assign": null,
   "_comments": null,
   "_liked_by": null,
   "_user_tags": null,
   "allow_in_quick_entry": 0,
   "allow_on_submit": 0,
   "bold": 0,
   "collapsible": 0,
   "collapsible_depends_on": null,
   "columns": 0,
   "creation": "2023-11-28 08:46:06.401194",
   "default": null,
   "depends_on": null,
   "description": null,
   "docstatus": 0,
   "dt": "Delivery Note",
   "fetch_from": null,
   "fetch_if_empty": 0,
   "fieldname": "custom_column_break_wfdyk",
   "fieldtype": "Column Break",
   "hidden": 0,
   "hide_border": 0,
   "hide_days": 0,
   "hide_seconds": 0,
   "idx": 24,
   "ignore_user_permissions": 0,
   "ignore_xss_filter": 0,
   "in_global_search": 0,
   "in_list_view": 0,
   "in_preview": 0,
   "in_standard_filter": 0,
   "insert_after": "accounting_dimensions_section",
   "is_system_generated": 0,
   "is_virtual": 0,
   "label": "",
   "length": 0,
   "mandatory_depends_on": null,
   "modified": "2023-11-28 08:46:06.401194",
   "modified_by": "Administrator",
   "module": null,
   "name": "Delivery Note-custom_column_break_wfdyk",
   "no_copy": 0,
   "non_negative": 0,
   "options": null,
   "owner": "Administrator",
   "permlevel": 0,
   "precision": "",
   "print_hide": 0,
   "print_hide_if_no_value": 0,
   "print_width": null,
   "read_only": 0,
   "read_only_depends_on": null,
   "report_hide": 0,
   "reqd": 0,
   "search_index": 0,
   "sort_options": 0,
   "translatable": 0,
   "unique": 0,
   "width": null
  },
  {
   "_assign": null,
   "_comments": null,
   "_liked_by": null,
   "_user_tags": null,
   "allow_in_quick_entry": 0,
   "allow_on_submit": 0,
   "bold": 0,
   "collapsible": 0,
   "collapsible_depends_on": null,
   "columns": 0,
   "creation": "2023-11-28 14:24:47.373245",
   "default": null,
   "depends_on": null,
   "description": null,
   "docstatus": 0,
   "dt": "Delivery Note",
   "fetch_from": null,
   "fetch_if_empty": 0,
   "fieldname": "custom_column_break_hzl7q",
   "fieldtype": "Column Break",
   "hidden": 0,
   "hide_border": 0,
   "hide_days": 0,
   "hide_seconds": 0,
   "idx": 66,
   "ignore_user_permissions": 0,
   "ignore_xss_filter": 0,
   "in_global_search": 0,
   "in_list_view": 0,
   "in_preview": 0,
   "in_standard_filter": 0,
   "insert_after": "section_break_41",
   "is_system_generated": 0,
   "is_virtual": 0,
   "label": "",
   "length": 0,
   "mandatory_depends_on": null,
   "modified": "2023-11-28 14:24:47.373245",
   "modified_by": "Administrator",
   "module": null,
   "name": "Delivery Note-custom_column_break_hzl7q",
   "no_copy": 0,
   "non_negative": 0,
   "options": null,
   "owner": "Administrator",
   "permlevel": 0,
   "precision": "",
   "print_hide": 0,
   "print_hide_if_no_value": 0,
   "print_width": null,
   "read_only": 0,
   "read_only_depends_on": "",
   "report_hide": 0,
   "reqd": 0,
   "search_index": 0,
   "sort_options": 0,
   "translatable": 0,
   "unique": 0,
   "width": null
  }
 ],
 "custom_perms": [],
 "doctype": "Delivery Note",
 "links": [],
 "property_setters": [
  {
   "_assign": null,
   "_comments": null,
   "_liked_by": null,
   "_user_tags": null,
   "creation": "2023-11-30 13:22:59.464353",
   "default_value": null,
   "doc_type": "Delivery Note",
   "docstatus": 0,
   "doctype_or_field": "DocType",
   "field_name": null,
   "idx": 0,
   "is_system_generated": 0,
   "modified": "2023-11-30 13:22:59.464353",
   "modified_by": "Administrator",
   "module": null,
   "name": "Delivery Note-main-field_order",
   "owner": "Administrator",
   "property": "field_order",
   "property_type": "Data",
   "row_name": null,
   "value": "[\"ksa_einv_qr\", \"title\", \"naming_series\", \"cost_center\", \"column_break1\", \"customer\", \"customer_name\", \"tax_id\", \"customer_name_in_arabic\", \"column_break_10\", \"posting_date\", \"posting_time\", \"set_posting_time\", \"company\", \"amended_from\", \"is_return\", \"issue_credit_note\", \"return_against\", \"customer_po_details\", \"po_no\", \"column_break_17\", \"po_date\", \"accounting_dimensions_section\", \"custom_column_break_wfdyk\", \"column_break_18\", \"project\", \"dimension_col_break\", \"currency_and_price_list\", \"currency\", \"conversion_rate\", \"col_break23\", \"selling_price_list\", \"price_list_currency\", \"plc_conversion_rate\", \"ignore_pricing_rule\", \"items_section\", \"set_warehouse\", \"scan_barcode\", \"pick_list\", \"col_break_warehouse\", \"set_target_warehouse\", \"section_break_30\", \"items\", \"section_break_31\", \"total_qty\", \"total_net_weight\", \"column_break_35\", \"additional_discount_percentage\", \"base_total\", \"base_net_total\", \"column_break_33\", \"total\", \"discount_amount\", \"net_total\", \"total_taxes_and_charges\", \"grand_total\", \"taxes_section\", \"tax_category\", \"taxes_and_charges\", \"column_break_43\", \"shipping_rule\", \"column_break_39\", \"incoterm\", \"named_place\", \"section_break_41\", \"custom_column_break_hzl7q\", \"taxes\", \"section_break_44\", \"base_total_taxes_and_charges\", \"column_break_47\", \"totals\", \"base_grand_total\", \"base_rounding_adjustment\", \"base_rounded_total\", \"base_in_words\", \"column_break3\", \"rounding_adjustment\", \"rounded_total\", \"in_words\", \"disable_rounded_total\", \"section_break_49\", \"apply_discount_on\", \"base_discount_amount\", \"column_break_51\", \"sec_tax_breakup\", \"other_charges_calculation\", \"packing_list\", \"packed_items\", \"product_bundle_help\", \"pricing_rule_details\", \"pricing_rules\", \"address_and_contact_tab\", \"contact_info\", \"customer_address\", \"address_display\", \"col_break21\", \"contact_person\", \"contact_display\", \"contact_mobile\", \"contact_email\", \"shipping_address_section\", \"shipping_address_name\", \"shipping_address\", \"column_break_95\", \"dispatch_address_name\", \"dispatch_address\", \"company_address_section\", \"company_address\", \"company_trn\", \"column_break_101\", \"company_address_display\", \"terms_tab\", \"tc_name\", \"terms\", \"more_info_tab\", \"section_break_83\", \"per_billed\", \"status\", \"column_break_112\", \"per_installed\", \"installation_status\", \"column_break_89\", \"per_returned\", \"transporter_info\", \"transporter\", \"driver\", \"lr_no\", \"vehicle_no\", \"col_break34\", \"transporter_name\", \"driver_name\", \"lr_date\", \"sales_team_section_break\", \"sales_partner\", \"amount_eligible_for_commission\", \"column_break7\", \"commission_rate\", \"total_commission\", \"section_break1\", \"sales_team\", \"subscription_section\", \"auto_repeat\", \"printing_details\", \"letter_head\", \"print_without_amount\", \"group_same_items\", \"column_break_88\", \"select_print_heading\", \"language\", \"more_info\", \"is_internal_customer\", \"represents_company\", \"inter_company_reference\", \"customer_group\", \"territory\", \"source\", \"campaign\", \"column_break5\", \"excise_page\", \"instructions\", \"connections_tab\"]"
  },
  {
   "_assign": null,
   "_comments": null,
   "_liked_by": null,
   "_user_tags": null,
   "creation": "2023-11-29 13:14:37.705381",
   "default_value": null,
   "doc_type": "Delivery Note",
   "docstatus": 0,
   "doctype_or_field": "DocField",
   "field_name": "in_words",
   "idx": 0,
   "is_system_generated": 0,
   "modified": "2023-11-29 13:14:37.705381",
   "modified_by": "Administrator",
   "module": null,
   "name": "Delivery Note-in_words-print_hide",
   "owner": "Administrator",
   "property": "print_hide",
   "property_type": "Check",
   "row_name": null,
   "value": "1"
  },
  {
   "_assign": null,
   "_comments": null,
   "_liked_by": null,
   "_user_tags": null,
   "creation": "2023-11-29 13:14:37.695857",
   "default_value": null,
   "doc_type": "Delivery Note",
   "docstatus": 0,
   "doctype_or_field": "DocField",
   "field_name": "in_words",
   "idx": 0,
   "is_system_generated": 0,
   "modified": "2023-11-29 13:14:37.695857",
   "modified_by": "Administrator",
   "module": null,
   "name": "Delivery Note-in_words-hidden",
   "owner": "Administrator",
   "property": "hidden",
   "property_type": "Check",
   "row_name": null,
   "value": "1"
  },
  {
   "_assign": null,
   "_comments": null,
   "_liked_by": null,
   "_user_tags": null,
   "creation": "2023-11-29 13:14:37.375224",
   "default_value": null,
   "doc_type": "Delivery Note",
   "docstatus": 0,
   "doctype_or_field": "DocField",
   "field_name": "disable_rounded_total",
   "idx": 0,
   "is_system_generated": 0,
   "modified": "2023-11-29 13:14:37.375224",
   "modified_by": "Administrator",
   "module": null,
   "name": "Delivery Note-disable_rounded_total-default",
   "owner": "Administrator",
   "property": "default",
   "property_type": "Text",
   "row_name": null,
   "value": "1"
  },
  {
   "_assign": null,
   "_comments": null,
   "_liked_by": null,
   "_user_tags": null,
   "creation": "2023-11-29 13:14:37.362975",
   "default_value": null,
   "doc_type": "Delivery Note",
   "docstatus": 0,
   "doctype_or_field": "DocField",
   "field_name": "rounded_total",
   "idx": 0,
   "is_system_generated": 0,
   "modified": "2023-11-29 13:14:37.362975",
   "modified_by": "Administrator",
   "module": null,
   "name": "Delivery Note-rounded_total-print_hide",
   "owner": "Administrator",
   "property": "print_hide",
   "property_type": "Check",
   "row_name": null,
   "value": "1"
  },
  {
   "_assign": null,
   "_comments": null,
   "_liked_by": null,
   "_user_tags": null,
   "creation": "2023-11-29 13:14:37.350726",
   "default_value": null,
   "doc_type": "Delivery Note",
   "docstatus": 0,
   "doctype_or_field": "DocField",
   "field_name": "rounded_total",
   "idx": 0,
   "is_system_generated": 0,
   "modified": "2023-11-29 13:14:37.350726",
   "modified_by": "Administrator",
   "module": null,
   "name": "Delivery Note-rounded_total-hidden",
   "owner": "Administrator",
   "property": "hidden",
   "property_type": "Check",
   "row_name": null,
   "value": "1"
  },
  {
   "_assign": null,
   "_comments": null,
   "_liked_by": null,
   "_user_tags": null,
   "creation": "2023-11-29 13:14:37.338911",
   "default_value": null,
   "doc_type": "Delivery Note",
   "docstatus": 0,
   "doctype_or_field": "DocField",
   "field_name": "base_rounded_total",
   "idx": 0,
   "is_system_generated": 0,
   "modified": "2023-11-29 13:14:37.338911",
   "modified_by": "Administrator",
   "module": null,
   "name": "Delivery Note-base_rounded_total-print_hide",
   "owner": "Administrator",
   "property": "print_hide",
   "property_type": "Check",
   "row_name": null,
   "value": "1"
  },
  {
   "_assign": null,
   "_comments": null,
   "_liked_by": null,
   "_user_tags": null,
   "creation": "2023-11-29 13:14:37.315162",
   "default_value": null,
   "doc_type": "Delivery Note",
   "docstatus": 0,
   "doctype_or_field": "DocField",
   "field_name": "base_rounded_total",
   "idx": 0,
   "is_system_generated": 0,
   "modified": "2023-11-29 13:14:37.315162",
   "modified_by": "Administrator",
   "module": null,
   "name": "Delivery Note-base_rounded_total-hidden",
   "owner": "Administrator",
   "property": "hidden",
   "property_type": "Check",
   "row_name": null,
   "value": "1"
  },
  {
   "_assign": null,
   "_comments": null,
   "_liked_by": null,
   "_user_tags": null,
   "creation": "2023-11-29 13:12:36.834437",
   "default_value": null,
   "doc_type": "Delivery Note",
   "docstatus": 0,
   "doctype_or_field": "DocField",
   "field_name": "tax_id",
   "idx": 0,
   "is_system_generated": 0,
   "modified": "2023-11-29 13:12:36.834437",
   "modified_by": "Administrator",
   "module": null,
   "name": "Delivery Note-tax_id-print_hide",
   "owner": "Administrator",
   "property": "print_hide",
   "property_type": "Check",
   "row_name": null,
   "value": "0"
  },
  {
   "_assign": null,
   "_comments": null,
   "_liked_by": null,
   "_user_tags": null,
   "creation": "2023-11-29 13:12:36.823021",
   "default_value": null,
   "doc_type": "Delivery Note",
   "docstatus": 0,
   "doctype_or_field": "DocField",
   "field_name": "tax_id",
   "idx": 0,
   "is_system_generated": 0,
   "modified": "2023-11-29 13:12:36.823021",
   "modified_by": "Administrator",
   "module": null,
   "name": "Delivery Note-tax_id-hidden",
   "owner": "Administrator",
   "property": "hidden",
   "property_type": "Check",
   "row_name": null,
   "value": "0"
  },
  {
   "_assign": null,
   "_comments": null,
   "_liked_by": null,
   "_user_tags": null,
   "creation": "2023-11-29 13:07:33.826622",
   "default_value": null,
   "doc_type": "Delivery Note",
   "docstatus": 0,
   "doctype_or_field": "DocField",
   "field_name": "scan_barcode",
   "idx": 0,
   "is_system_generated": 1,
   "modified": "2023-11-29 13:07:33.826622",
   "modified_by": "Administrator",
   "module": null,
   "name": "Delivery Note-scan_barcode-hidden",
   "owner": "Administrator",
   "property": "hidden",
   "property_type": "Check",
   "row_name": null,
   "value": "1"
  },
  {
   "_assign": null,
   "_comments": null,
   "_liked_by": null,
   "_user_tags": null,
   "creation": "2023-11-29 10:20:56.693716",
   "default_value": null,
   "doc_type": "Delivery Note",
   "docstatus": 0,
   "doctype_or_field": "DocField",
   "field_name": "discount_amount",
   "idx": 0,
   "is_system_generated": 0,
   "modified": "2023-11-29 10:20:56.693716",
   "modified_by": "Administrator",
   "module": null,
   "name": "Delivery Note-discount_amount-depends_on",
   "owner": "Administrator",
   "property": "depends_on",
   "property_type": "Data",
   "row_name": null,
   "value": ""
  },
  {
   "_assign": null,
   "_comments": null,
   "_liked_by": null,
   "_user_tags": null,
   "creation": "2023-11-29 10:15:38.507098",
   "default_value": null,
   "doc_type": "Delivery Note",
   "docstatus": 0,
   "doctype_or_field": "DocField",
   "field_name": "apply_discount_on",
   "idx": 0,
   "is_system_generated": 0,
   "modified": "2023-11-29 10:15:38.507098",
   "modified_by": "Administrator",
   "module": null,
   "name": "Delivery Note-apply_discount_on-depends_on",
   "owner": "Administrator",
   "property": "depends_on",
   "property_type": "Data",
   "row_name": null,
   "value": "eval:frappe.user.has_role('Administrator') === true"
  },
  {
   "_assign": null,
   "_comments": null,
   "_liked_by": null,
   "_user_tags": null,
   "creation": "2023-11-29 09:59:27.320914",
   "default_value": null,
   "doc_type": "Delivery Note",
   "docstatus": 0,
   "doctype_or_field": "DocField",
   "field_name": "column_break_17",
   "idx": 0,
   "is_system_generated": 0,
   "modified": "2023-11-29 09:59:27.320914",
   "modified_by": "Administrator",
   "module": null,
   "name": "Delivery Note-column_break_17-hidden",
   "owner": "Administrator",
   "property": "hidden",
   "property_type": "Check",
   "row_name": null,
   "value": "1"
  },
  {
   "_assign": null,
   "_comments": null,
   "_liked_by": null,
   "_user_tags": null,
   "creation": "2023-11-28 14:27:18.269010",
   "default_value": null,
   "doc_type": "Delivery Note",
   "docstatus": 0,
   "doctype_or_field": "DocField",
   "field_name": "taxes",
   "idx": 0,
   "is_system_generated": 0,
   "modified": "2023-11-28 14:27:18.269010",
   "modified_by": "Administrator",
   "module": null,
   "name": "Delivery Note-taxes-read_only_depends_on",
   "owner": "Administrator",
   "property": "read_only_depends_on",
   "property_type": "Data",
   "row_name": null,
   "value": ""
  },
  {
   "_assign": null,
   "_comments": null,
   "_liked_by": null,
   "_user_tags": null,
   "creation": "2023-11-28 14:15:44.875184",
   "default_value": null,
   "doc_type": "Delivery Note",
   "docstatus": 0,
   "doctype_or_field": "DocField",
   "field_name": "more_info",
   "idx": 0,
   "is_system_generated": 0,
   "modified": "2023-11-28 14:15:44.875184",
   "modified_by": "Administrator",
   "module": null,
   "name": "Delivery Note-more_info-depends_on",
   "owner": "Administrator",
   "property": "depends_on",
   "property_type": "Data",
   "row_name": null,
   "value": "eval:frappe.user.has_role('Administrator') === true"
  },
  {
   "_assign": null,
   "_comments": null,
   "_liked_by": null,
   "_user_tags": null,
   "creation": "2023-11-28 14:15:44.753504",
   "default_value": null,
   "doc_type": "Delivery Note",
   "docstatus": 0,
   "doctype_or_field": "DocField",
   "field_name": "printing_details",
   "idx": 0,
   "is_system_generated": 0,
   "modified": "2023-11-28 14:15:44.753504",
   "modified_by": "Administrator",
   "module": null,
   "name": "Delivery Note-printing_details-depends_on",
   "owner": "Administrator",
   "property": "depends_on",
   "property_type": "Data",
   "row_name": null,
   "value": "eval:frappe.user.has_role('Administrator') === true"
  },
  {
   "_assign": null,
   "_comments": null,
   "_liked_by": null,
   "_user_tags": null,
   "creation": "2023-11-28 14:13:58.168647",
   "default_value": null,
   "doc_type": "Delivery Note",
   "docstatus": 0,
   "doctype_or_field": "DocField",
   "field_name": "transporter_info",
   "idx": 0,
   "is_system_generated": 0,
   "modified": "2023-11-28 14:13:58.168647",
   "modified_by": "Administrator",
   "module": null,
   "name": "Delivery Note-transporter_info-depends_on",
   "owner": "Administrator",
   "property": "depends_on",
   "property_type": "Data",
   "row_name": null,
   "value": "eval:frappe.user.has_role('Administrator') === true"
  },
  {
   "_assign": null,
   "_comments": null,
   "_liked_by": null,
   "_user_tags": null,
   "creation": "2023-11-28 14:09:56.909461",
   "default_value": null,
   "doc_type": "Delivery Note",
   "docstatus": 0,
   "doctype_or_field": "DocField",
   "field_name": "cost_center",
   "idx": 0,
   "is_system_generated": 0,
   "modified": "2023-11-28 14:09:56.909461",
   "modified_by": "Administrator",
   "module": null,
   "name": "Delivery Note-cost_center-label",
   "owner": "Administrator",
   "property": "label",
   "property_type": "Data",
   "row_name": null,
   "value": "Branch"
  },
  {
   "_assign": null,
   "_comments": null,
   "_liked_by": null,
   "_user_tags": null,
   "creation": "2023-11-28 13:42:18.072169",
   "default_value": null,
   "doc_type": "Delivery Note",
   "docstatus": 0,
   "doctype_or_field": "DocField",
   "field_name": "disable_rounded_total",
   "idx": 0,
   "is_system_generated": 0,
   "modified": "2023-11-28 13:42:18.072169",
   "modified_by": "Administrator",
   "module": null,
   "name": "Delivery Note-disable_rounded_total-depends_on",
   "owner": "Administrator",
   "property": "depends_on",
   "property_type": "Data",
   "row_name": null,
   "value": "eval:frappe.user.has_role('Administrator') === true"
  },
  {
   "_assign": null,
   "_comments": null,
   "_liked_by": null,
   "_user_tags": null,
   "creation": "2023-11-28 13:38:55.602292",
   "default_value": null,
   "doc_type": "Delivery Note",
   "docstatus": 0,
   "doctype_or_field": "DocField",
   "field_name": "apply_discount_on",
   "idx": 0,
   "is_system_generated": 0,
   "modified": "2023-11-28 13:38:55.602292",
   "modified_by": "Administrator",
   "module": null,
   "name": "Delivery Note-apply_discount_on-read_only",
   "owner": "Administrator",
   "property": "read_only",
   "property_type": "Check",
   "row_name": null,
   "value": "1"
  },
  {
   "_assign": null,
   "_comments": null,
   "_liked_by": null,
   "_user_tags": null,
   "creation": "2023-11-28 13:38:25.066043",
   "default_value": null,
   "doc_type": "Delivery Note",
   "docstatus": 0,
   "doctype_or_field": "DocField",
   "field_name": "apply_discount_on",
   "idx": 0,
   "is_system_generated": 0,
   "modified": "2023-11-28 13:38:25.066043",
   "modified_by": "Administrator",
   "module": null,
   "name": "Delivery Note-apply_discount_on-default",
   "owner": "Administrator",
   "property": "default",
   "property_type": "Text",
   "row_name": null,
   "value": "Net Total"
  },
  {
   "_assign": null,
   "_comments": null,
   "_liked_by": null,
   "_user_tags": null,
   "creation": "2023-11-28 13:35:35.854145",
   "default_value": null,
   "doc_type": "Delivery Note",
   "docstatus": 0,
   "doctype_or_field": "DocField",
   "field_name": "total_qty",
   "idx": 0,
   "is_system_generated": 0,
   "modified": "2023-11-28 13:35:35.854145",
   "modified_by": "Administrator",
   "module": null,
   "name": "Delivery Note-total_qty-depends_on",
   "owner": "Administrator",
   "property": "depends_on",
   "property_type": "Data",
   "row_name": null,
   "value": "eval:frappe.user.has_role('Administrator') === true"
  },
  {
   "_assign": null,
   "_comments": null,
   "_liked_by": null,
   "_user_tags": null,
   "creation": "2023-11-28 13:27:42.268291",
   "default_value": null,
   "doc_type": "Delivery Note",
   "docstatus": 0,
   "doctype_or_field": "DocField",
   "field_name": "discount_amount",
   "idx": 0,
   "is_system_generated": 0,
   "modified": "2023-11-28 13:27:42.268291",
   "modified_by": "Administrator",
   "module": null,
   "name": "Delivery Note-discount_amount-label",
   "owner": "Administrator",
   "property": "label",
   "property_type": "Data",
   "row_name": null,
   "value": "Discount Amount"
  },
  {
   "_assign": null,
   "_comments": null,
   "_liked_by": null,
   "_user_tags": null,
   "creation": "2023-11-28 13:27:42.173981",
   "default_value": null,
   "doc_type": "Delivery Note",
   "docstatus": 0,
   "doctype_or_field": "DocField",
   "field_name": "additional_discount_percentage",
   "idx": 0,
   "is_system_generated": 0,
   "modified": "2023-11-28 13:27:42.173981",
   "modified_by": "Administrator",
   "module": null,
   "name": "Delivery Note-additional_discount_percentage-label",
   "owner": "Administrator",
   "property": "label",
   "property_type": "Data",
   "row_name": null,
   "value": "Discount Percentage"
  },
  {
   "_assign": null,
   "_comments": null,
   "_liked_by": null,
   "_user_tags": null,
   "creation": "2023-11-28 13:27:42.075598",
   "default_value": null,
   "doc_type": "Delivery Note",
   "docstatus": 0,
   "doctype_or_field": "DocField",
   "field_name": "apply_discount_on",
   "idx": 0,
   "is_system_generated": 0,
   "modified": "2023-11-28 13:27:42.075598",
   "modified_by": "Administrator",
   "module": null,
   "name": "Delivery Note-apply_discount_on-label",
   "owner": "Administrator",
   "property": "label",
   "property_type": "Data",
   "row_name": null,
   "value": "Additional Discount On"
  },
  {
   "_assign": null,
   "_comments": null,
   "_liked_by": null,
   "_user_tags": null,
   "creation": "2023-11-28 12:59:57.988243",
   "default_value": null,
   "doc_type": "Delivery Note",
   "docstatus": 0,
   "doctype_or_field": "DocField",
   "field_name": "taxes_section",
   "idx": 0,
   "is_system_generated": 0,
   "modified": "2023-11-28 12:59:57.988243",
   "modified_by": "Administrator",
   "module": null,
   "name": "Delivery Note-taxes_section-depends_on",
   "owner": "Administrator",
   "property": "depends_on",
   "property_type": "Data",
   "row_name": null,
   "value": "eval:frappe.user.has_role('Administrator') === true"
  },
  {
   "_assign": null,
   "_comments": null,
   "_liked_by": null,
   "_user_tags": null,
   "creation": "2023-11-28 12:57:10.009673",
   "default_value": null,
   "doc_type": "Delivery Note",
   "docstatus": 0,
   "doctype_or_field": "DocField",
   "field_name": "scan_barcode",
   "idx": 0,
   "is_system_generated": 0,
   "modified": "2023-11-28 12:57:10.009673",
   "modified_by": "Administrator",
   "module": null,
   "name": "Delivery Note-scan_barcode-depends_on",
   "owner": "Administrator",
   "property": "depends_on",
   "property_type": "Data",
   "row_name": null,
   "value": "eval:frappe.user.has_role('Administrator') === true"
  },
  {
   "_assign": null,
   "_comments": null,
   "_liked_by": null,
   "_user_tags": null,
   "creation": "2023-11-28 12:57:09.909688",
   "default_value": null,
   "doc_type": "Delivery Note",
   "docstatus": 0,
   "doctype_or_field": "DocField",
   "field_name": "accounting_dimensions_section",
   "idx": 0,
   "is_system_generated": 0,
   "modified": "2023-11-28 12:57:09.909688",
   "modified_by": "Administrator",
   "module": null,
   "name": "Delivery Note-accounting_dimensions_section-depends_on",
   "owner": "Administrator",
   "property": "depends_on",
   "property_type": "Data",
   "row_name": null,
   "value": "eval:frappe.user.has_role('Administrator') === true"
  },
  {
   "_assign": null,
   "_comments": null,
   "_liked_by": null,
   "_user_tags": null,
   "creation": "2023-11-28 08:46:06.291141",
   "default_value": null,
   "doc_type": "Delivery Note",
   "docstatus": 0,
   "doctype_or_field": "DocField",
   "field_name": "cost_center",
   "idx": 0,
   "is_system_generated": 0,
   "modified": "2023-11-28 08:46:06.291141",
   "modified_by": "Administrator",
   "module": null,
   "name": "Delivery Note-cost_center-reqd",
   "owner": "Administrator",
   "property": "reqd",
   "property_type": "Check",
   "row_name": null,
   "value": "1"
  }
 ],
 "sync_on_migrate": 1
}